SecondOrderElec/__init__.py
SecondOrderElec/core.py
SecondOrderElec/plot.py
SecondOrderElec/tools.py
SecondOrderElec/version.py
SecondOrderElec-0.0.4.dist-info/LICENCE
SecondOrderElec-0.0.4.dist-info/METADATA
SecondOrderElec-0.0.4.dist-info/WHEEL
SecondOrderElec-0.0.4.dist-info/top_level.txt
SecondOrderElec-0.0.4.dist-info/RECORD
