Metadata-Version: 2.1
Name: SecondOrderElec
Version: 0.0.4
Summary: A python module to work with continuous-time system. You will find various second order electronic filters models.
Home-page: https://github.com/slashformotion/SecondOrderElec
Author: slashformotion
Author-email: slashformotion@protonmail.com
License: MIT
Platform: UNKNOWN
Classifier: Development Status :: 2 - Pre-Alpha
Classifier: Intended Audience :: Developers
Classifier: License :: OSI Approved :: MIT License
Classifier: Programming Language :: Python :: 3.6
Classifier: Programming Language :: Python :: 3.7
Classifier: Programming Language :: Python :: 3.8
Classifier: Programming Language :: Python :: 3.9
Requires-Python: >=3.6
Requires-Dist: matplotlib
Requires-Dist: numpy
Requires-Dist: scipy
